neuromeka_lib/__init__.py
neuromeka_lib/install.py
neuromeka_install_lib-0.0.2.dist-info/METADATA
neuromeka_install_lib-0.0.2.dist-info/WHEEL
neuromeka_install_lib-0.0.2.dist-info/entry_points.txt
neuromeka_install_lib-0.0.2.dist-info/top_level.txt
neuromeka_install_lib-0.0.2.dist-info/RECORD
