Metadata-Version: 2.1
Name: neuromeka_install_lib
Version: 0.0.2
Summary: Neuromeka library package
Author: Neuromeka
Author-email: technical-support@neuromeka.com
Requires-Python: >=3.6
